mimicpy/__init__.py
mimicpy/__main__.py
mimicpy/__main_vmd__.py
mimicpy/_authors.py
mimicpy/_version.py
mimicpy/coords/__init__.py
mimicpy/coords/base.py
mimicpy/coords/gro.py
mimicpy/coords/pdb.py
mimicpy/core/__init__.py
mimicpy/core/prepare.py
mimicpy/core/selector.py
mimicpy/scripts/__init__.py
mimicpy/scripts/cpmd.py
mimicpy/scripts/mdp.py
mimicpy/scripts/ndx.py
mimicpy/scripts/script.py
mimicpy/topology/__init__.py
mimicpy/topology/itp.py
mimicpy/topology/mpt.py
mimicpy/topology/top.py
mimicpy/topology/topol_dict.py
mimicpy/utils/__init__.py
mimicpy/utils/atomic_numbers.py
mimicpy/utils/constants.py
mimicpy/utils/elements.py
mimicpy/utils/errors.py
mimicpy/utils/file_handler.py
mimicpy/utils/strings.py
mimicpy-0.1.0.dist-info/LICENSE
mimicpy-0.1.0.dist-info/METADATA
mimicpy-0.1.0.dist-info/WHEEL
mimicpy-0.1.0.dist-info/entry_points.txt
mimicpy-0.1.0.dist-info/top_level.txt
mimicpy-0.1.0.dist-info/zip-safe
mimicpy-0.1.0.dist-info/RECORD
