Metadata-Version: 2.1
Name: mimicpy
Version: 0.1.0
Summary: Python tools to prepare MiMiC QM/MM runs.
Home-page: https://github.com/bharurn/mimicpy
Author: Bharath Raghavan and Florian Schackert
Author-email: b.raghavan@fz-juelich.de
License: GNU General Public License v3.0
Platform: OS Independent
Classifier: Programming Language :: Python :: 3
Classifier: License :: OSI Approved :: GNU General Public License v3 (GPLv3)
Classifier: Operating System :: OS Independent
Requires-Python: >=3.5
License-File: LICENSE
Requires-Dist: numpy (>=1.12.0)
Requires-Dist: pandas (>=0.24.0)
